django_historique
