Metadata-Version: 1.0
Name: django-historique
Version: 1.0.1
Summary: Save revisions of your objects in another table!
Home-page: http://code.google.com/p/django-historique/
Author: Cyril Robert
Author-email: cyril.robert@auf.org
License: GPL
Download-URL: http://pypi.python.org/pypi/django_historique/1.0
Keywords: django,history,diff
Platform: UNKNOWN
Classifier: Environment :: Web Environment
Classifier: Framework :: Django
Classifier: Intended Audience :: Developers
Classifier: Intended Audience :: End Users/Desktop
Classifier: License :: OSI Approved :: GNU General Public License (GPL)
Classifier: Natural Language :: English
Classifier: Operating System :: OS Independent
Classifier: Programming Language :: Python
Classifier: Topic :: Internet :: WWW/HTTP :: Dynamic Content :: CGI Tools/Libraries
